{
	"cat": [
		{
			"photo": "img/adamcatlace.png",
			"name": "Adam Catlace",
			"age": 3
		},
		{
			"photo": "img/tpl.jpg",
			"name": "Tim Purrners-Lee"
		},
		{
			"photo": "img/alanpurring.jpg",
			"name": "Alan Purring",
			"age": 7
		},
		{
			"photo": "img/vector.jpg",
			"name": "Vector",
			"age": 12
		},
		{
			"photo": "img/shrodingcat.png",
			"name": "Schrödingcat",
			"age": "-3"
		},
		{},
		{
			"photo": "https://cdn.rawgit.com/dkhuntrods/mv-data/c360ebb87906e9948de48ea624e5d67c8f6e2f92/images/IMG_20171007_155353.jpg",
			"name": "Chocolate",
			"age": "2"
		}
	]
}